<?xml version="1.0"?><Shapes><shape>
	<type>2</type>
	<x1>472</x1>
	<y1>131</y1>
	<x2>69</x2>
	<y2>308</y2>
	<fontColor>null</fontColor>
	<fillColor>null</fillColor>
</shape>
<shape>
	<type>2</type>
	<x1>816</x1>
	<y1>118</y1>
	<x2>626</x2>
	<y2>278</y2>
	<fontColor>null</fontColor>
	<fillColor>null</fillColor>
</shape>
<shape>
	<type>2</type>
	<x1>472</x1>
	<y1>131</y1>
	<x2>69</x2>
	<y2>308</y2>
	<fontColor>null</fontColor>
	<fillColor>null</fillColor>
</shape>
<shape>
	<type>2</type>
	<x1>816</x1>
	<y1>118</y1>
	<x2>626</x2>
	<y2>278</y2>
	<fontColor>null</fontColor>
	<fillColor>null</fillColor>
</shape>
</Shapes>
